spawn_parallel_instances/__init__.py
spawn_parallel_instances/__main__.py
spawn_parallel_instances-1.1.0.dist-info/LICENSE
spawn_parallel_instances-1.1.0.dist-info/METADATA
spawn_parallel_instances-1.1.0.dist-info/WHEEL
spawn_parallel_instances-1.1.0.dist-info/entry_points.txt
spawn_parallel_instances-1.1.0.dist-info/top_level.txt
spawn_parallel_instances-1.1.0.dist-info/RECORD
