Metadata-Version: 2.1
Name: spawn_parallel_instances
Version: 1.1.0
Summary: A package to run multiple instances of the same script.
Home-page: https://github.com/stenzr/spawn_parallel_instances
Author: Rohit Kumar
Author-email: rkrohitkr01@gmail.com
License: MIT
Requires-Python: >=3.6
License-File: LICENSE
Requires-Dist: PyYAML ==6.0.2rc1
Requires-Dist: setuptools ==71.1.0
Requires-Dist: bump2version ==1.0.1
Requires-Dist: bumpversion ==0.6.0
Requires-Dist: requests ==2.32.3
Provides-Extra: test
Requires-Dist: unittest ; extra == 'test'
Requires-Dist: coverage ; extra == 'test'
